[
  {
    "name":"Powerplay ranks",
    "types":[
      {
        "name": "Rank 1",
        "preview":"/static/img/preview/powerplay/ranks/rank1.png",
        "desc": "First rank of powerplay.",
        "fanmade": true,
        "designer_info": [
          {
            "name":"CMDR Zhincore",
            "url":"https://github.com/Zhincore"
          }
        ],
        "formats": [
          {
            "format":"PNG",
            "link":"/static/img/powerplay/ranks/rank1.png"
          },
          {
            "format":"SVG",
            "link":"/static/img/powerplay/ranks/rank1.svg"
          }
        ]
      },
      {
        "name": "Rank 2",
        "preview":"/static/img/preview/powerplay/ranks/rank2.png",
        "desc": "Second rank of powerplay.",
        "fanmade": true,
        "designer_info": [
          {
            "name":"CMDR Zhincore",
            "url":"https://github.com/Zhincore"
          }
        ],
        "formats": [
          {
            "format":"PNG",
            "link":"/static/img/powerplay/ranks/rank2.png"
          },
          {
            "format":"SVG",
            "link":"/static/img/powerplay/ranks/rank2.svg"
          }
        ]
      },
      {
        "name": "Rank 3",
        "preview":"/static/img/preview/powerplay/ranks/rank3.png",
        "desc": "Third rank of powerplay.",
        "fanmade": true,
        "designer_info": [
          {
            "name":"CMDR Zhincore",
            "url":"https://github.com/Zhincore"
          }
        ],
        "formats": [
          {
            "format":"PNG",
            "link":"/static/img/powerplay/ranks/rank3.png"
          },
          {
            "format":"SVG",
            "link":"/static/img/powerplay/ranks/rank3.svg"
          }
        ]
      },
      {
        "name": "Rank 4",
        "preview":"/static/img/preview/powerplay/ranks/rank4.png",
        "desc": "Fourth rank of powerplay.",
        "fanmade": true,
        "designer_info": [
          {
            "name":"CMDR Zhincore",
            "url":"https://github.com/Zhincore"
          }
        ],
        "formats": [
          {
            "format":"PNG",
            "link":"/static/img/powerplay/ranks/rank4.png"
          },
          {
            "format":"SVG",
            "link":"/static/img/powerplay/ranks/rank4.svg"
          }
        ]
      },
      {
        "name": "Rank 5",
        "preview":"/static/img/preview/powerplay/ranks/rank5.png",
        "desc": "Fifth rank of powerplay.",
        "fanmade": true,
        "designer_info": [
          {
            "name":"CMDR Zhincore",
            "url":"https://github.com/Zhincore"
          }
        ],
        "formats": [
          {
            "format":"PNG",
            "link":"/static/img/powerplay/ranks/rank5.png"
          },
          {
            "format":"SVG",
            "link":"/static/img/powerplay/ranks/rank5.svg"
          }
        ]
      }
    ]
  }
]
